pycart/__init__.py
pycart/border_util.py
pycart/cartogram.py
pycart-0.2.0.dist-info/LICENSE
pycart-0.2.0.dist-info/METADATA
pycart-0.2.0.dist-info/WHEEL
pycart-0.2.0.dist-info/RECORD
