Metadata-Version: 2.1
Name: pycart
Version: 0.2.0
Summary: A Python package for generating Cartograms using GeoDataFrames.
Home-page: https://github.com/ARundle01/ecmm428-pycart
License: BSD-3-Clause
Author: Alex Rundle
Author-email: alexrundle01@gmail.com
Requires-Python: >=3.9.7,<3.10
Classifier: Development Status :: 2 - Pre-Alpha
Classifier: Intended Audience :: Developers
Classifier: Intended Audience :: Science/Research
Classifier: License :: OSI Approved :: BSD License
Classifier: Operating System :: OS Independent
Classifier: Programming Language :: Python :: 3
Classifier: Topic :: Scientific/Engineering :: Visualization
Classifier: Topic :: Software Development
Requires-Dist: alive-progress (>=3.1.1,<4.0.0)
Requires-Dist: beautifulsoup4 (==4.12.0)
Requires-Dist: fonttools (==4.39.2)
Requires-Dist: geojson (==3.0.1)
Requires-Dist: geopandas (==0.12.2)
Requires-Dist: importlib-metadata (==6.1.0)
Requires-Dist: jinja2 (==3.0.3)
Requires-Dist: libpysal (==4.7.0)
Requires-Dist: matplotlib (==3.7.1)
Requires-Dist: mkdocs (==1.4.2)
Requires-Dist: mkdocstrings[python] (>=0.21.2,<0.22.0)
Requires-Dist: numpy (==1.24.2)
Requires-Dist: pandas (==1.5.3)
Requires-Dist: pillow (==9.4.0)
Requires-Dist: pyproj (==3.4.1)
Requires-Dist: pytz (==2023.2)
Requires-Dist: shapely (==2.0.1)
Project-URL: Documentation, https://ecmm428-pycart.readthedocs.io/
Project-URL: Repository, https://github.com/ARundle01/ecmm428-pycart
